woe_iv/__init__.py
woe_iv/cli.py
woe_iv/woe_iv.py
woe_iv-0.2.0.dist-info/METADATA
woe_iv-0.2.0.dist-info/RECORD
woe_iv-0.2.0.dist-info/WHEEL
woe_iv-0.2.0.dist-info/entry_points.txt
woe_iv-0.2.0.dist-info/top_level.txt
