Metadata-Version: 2.1
Name: woe-iv
Version: 0.2.0
Summary: caculate woe(weight of evidence) of each feature and then iv(information value).
Home-page: https://github.com/helloourworld/woe_iv
Author: David Yu (KPMG)
Author-email: davidyjun@gmail.com
License: UNKNOWN
Keywords: woe_iv
Platform: UNKNOWN
Classifier: Development Status :: 2 - Pre-Alpha
Classifier: Intended Audience :: Developers
Classifier: Natural Language :: English
Classifier: Programming Language :: Python :: 2
Classifier: Programming Language :: Python :: 2.7
Classifier: Programming Language :: Python :: 3
Classifier: Programming Language :: Python :: 3.4
Classifier: Programming Language :: Python :: 3.5
Classifier: Programming Language :: Python :: 3.6
Classifier: Programming Language :: Python :: 3.7
